aiohttp_rest_api/__init__.py
aiohttp_rest_api/__version__.py
aiohttp_rest_api/loader.py
aiohttp_rest_api/responses.py
aiohttp_rest_api/swagger.py
example/__init__.py
example/main.py
example/endpoints/__init__.py
example/endpoints/demo_endpoint.py
example/endpoints/demo_exception_endpoint.py
aiohttp_rest_api-0.0.6.dist-info/LICENSE
aiohttp_rest_api-0.0.6.dist-info/METADATA
aiohttp_rest_api-0.0.6.dist-info/WHEEL
aiohttp_rest_api-0.0.6.dist-info/top_level.txt
aiohttp_rest_api-0.0.6.dist-info/RECORD
